robo_orchard_schemas/__init__.py
robo_orchard_schemas/version.py
robo_orchard_schemas/action_msgs/instruction_pb2.py
robo_orchard_schemas/action_msgs/instruction_pb2.pyi
robo_orchard_schemas/action_msgs/task_pb2.py
robo_orchard_schemas/action_msgs/task_pb2.pyi
robo_orchard_schemas/dataset_msgs/Droid_pb2.py
robo_orchard_schemas/dataset_msgs/Droid_pb2.pyi
robo_orchard_schemas/geometry_msgs/TransformInFrame_pb2.py
robo_orchard_schemas/geometry_msgs/TransformInFrame_pb2.pyi
robo_orchard_schemas/robot_msgs/urdf_pb2.py
robo_orchard_schemas/robot_msgs/urdf_pb2.pyi
robo_orchard_schemas/sensor_msgs/JointState_pb2.py
robo_orchard_schemas/sensor_msgs/JointState_pb2.pyi
robo_orchard_schemas/std_msgs/Array_pb2.py
robo_orchard_schemas/std_msgs/Array_pb2.pyi
robo_orchard_schemas-0.1.1.dist-info/licenses/LICENSE
robo_orchard_schemas-0.1.1.dist-info/METADATA
robo_orchard_schemas-0.1.1.dist-info/WHEEL
robo_orchard_schemas-0.1.1.dist-info/top_level.txt
robo_orchard_schemas-0.1.1.dist-info/RECORD
